Workbook

Sheet Agent View
A1: Mercury Call Desk — Agent Pricing & Commission
A2: What agents see: retail, partner wholesale (your cost basis), gross profit, and your commission. Commission = split x (Retail - Wholesale - Stripe).
A4: INPUTS
A5: Stripe % | B5: 0.029
A6: Stripe fixed | B6: 0.3
A7: Site annual discount | B7: 0.25
A8: Enterprise annual discount | B8: 0.2
A9: Agent % — Site | B9: 0.5
A10: Agent % — Enterprise | B10: 0.5
A12: SET 1 — SITE / STANDARD
A13: Tier | B13: Retail $/mo | C13: Partner wholesale/mo | D13: Stripe fee/mo | E13: Gross profit/mo | F13: Agent commission/mo | G13: Annual billed/yr | H13: Gross profit/yr | I13: Agent commission/yr
A14: Starter | B14: 1595 | C14: 1000 | D14: =B14*$B$5+$B$6 -> 46.555 | E14: =B14-C14-D14 -> 548.445 | F14: =E14*$B$9 -> 274.2225 | G14: =B14*12*(1-$B$7) -> 14355 | H14: =G14-(G14*$B$5+$B$6)-(C14*12) -> 1938.405 | I14: =H14*$B$9 -> 969.2025
A15: Growth | B15: 1995 | C15: 1250 | D15: =B15*$B$5+$B$6 -> 58.155 | E15: =B15-C15-D15 -> 686.845 | F15: =E15*$B$9 -> 343.4225 | G15: =B15*12*(1-$B$7) -> 17955 | H15: =G15-(G15*$B$5+$B$6)-(C15*12) -> 2434.005 | I15: =H15*$B$9 -> 1217.0025
A16: Pro | B16: 3995 | C16: 1500 | D16: =B16*$B$5+$B$6 -> 116.155 | E16: =B16-C16-D16 -> 2378.845 | F16: =E16*$B$9 -> 1189.4225 | G16: =B16*12*(1-$B$7) -> 35955 | H16: =G16-(G16*$B$5+$B$6)-(C16*12) -> 16912.005 | I16: =H16*$B$9 -> 8456.0025
A18: SET 2 — ENTERPRISE
A19: Tier | B19: Retail $/mo | C19: Partner wholesale/mo | D19: Stripe fee/mo | E19: Gross profit/mo | F19: Agent commission/mo | G19: Annual billed/yr | H19: Gross profit/yr | I19: Agent commission/yr
A20: Starter | B20: 5295 | C20: 2500 | D20: =B20*$B$5+$B$6 -> 153.855 | E20: =B20-C20-D20 -> 2641.145 | F20: =E20*$B$10 -> 1320.5725 | G20: =B20*12*(1-$B$8) -> 50832 | H20: =G20-(G20*$B$5+$B$6)-(C20*12) -> 19357.572 | I20: =H20*$B$10 -> 9678.786
A21: Growth | B21: 7595 | C21: 3500 | D21: =B21*$B$5+$B$6 -> 220.555 | E21: =B21-C21-D21 -> 3874.445 | F21: =E21*$B$10 -> 1937.2225 | G21: =B21*12*(1-$B$8) -> 72912 | H21: =G21-(G21*$B$5+$B$6)-(C21*12) -> 28797.252 | I21: =H21*$B$10 -> 14398.626
A22: Pro | B22: 9995 | C22: 5000 | D22: =B22*$B$5+$B$6 -> 290.155 | E22: =B22-C22-D22 -> 4704.845 | F22: =E22*$B$10 -> 2352.4225 | G22: =B22*12*(1-$B$8) -> 95952 | H22: =G22-(G22*$B$5+$B$6)-(C22*12) -> 33169.092 | I22: =H22*$B$10 -> 16584.546

Sheet Internal (Confidential)
A1: INTERNAL / CONFIDENTIAL — DO NOT SHARE WITH AGENTS
A2: Your true economics. True cost is your real Sulus/dev cost. Hidden margin = partner wholesale shown to agents - true cost. Company net = true gross profit - agent commission.
A4: SET 1 — SITE / STANDARD
A5: Tier | B5: Retail/mo | C5: Partner wholesale/mo | D5: True cost/mo | E5: Hidden margin/mo | F5: Stripe/mo | G5: True gross profit/mo | H5: Agent commission/mo | I5: Company net/mo
A6: Starter | B6: ='Agent View'!B14 -> 1595 | C6: ='Agent View'!C14 -> 1000 | D6: 50 | E6: =C6-D6 -> 950 | F6: ='Agent View'!D14 -> 46.555 | G6: =B6-D6-F6 -> 1498.445 | H6: ='Agent View'!F14 -> 274.2225 | I6: =G6-H6 -> 1224.2225
A7: Growth | B7: ='Agent View'!B15 -> 1995 | C7: ='Agent View'!C15 -> 1250 | D7: 150 | E7: =C7-D7 -> 1100 | F7: ='Agent View'!D15 -> 58.155 | G7: =B7-D7-F7 -> 1786.845 | H7: ='Agent View'!F15 -> 343.4225 | I7: =G7-H7 -> 1443.4225
A8: Pro | B8: ='Agent View'!B16 -> 3995 | C8: ='Agent View'!C16 -> 1500 | D8: 500 | E8: =C8-D8 -> 1000 | F8: ='Agent View'!D16 -> 116.155 | G8: =B8-D8-F8 -> 3378.845 | H8: ='Agent View'!F16 -> 1189.4225 | I8: =G8-H8 -> 2189.4225
A10: SET 2 — ENTERPRISE
A11: Tier | B11: Retail/mo | C11: Partner wholesale/mo | D11: True cost/mo | E11: Hidden margin/mo | F11: Stripe/mo | G11: True gross profit/mo | H11: Agent commission/mo | I11: Company net/mo
A12: Starter | B12: ='Agent View'!B20 -> 5295 | C12: ='Agent View'!C20 -> 2500 | D12: 2500 | E12: =C12-D12 -> 0 | F12: ='Agent View'!D20 -> 153.855 | G12: =B12-D12-F12 -> 2641.145 | H12: ='Agent View'!F20 -> 1320.5725 | I12: =G12-H12 -> 1320.5725
A13: Growth | B13: ='Agent View'!B21 -> 7595 | C13: ='Agent View'!C21 -> 3500 | D13: 3500 | E13: =C13-D13 -> 0 | F13: ='Agent View'!D21 -> 220.555 | G13: =B13-D13-F13 -> 3874.445 | H13: ='Agent View'!F21 -> 1937.2225 | I13: =G13-H13 -> 1937.2225
A14: Pro | B14: ='Agent View'!B22 -> 9995 | C14: ='Agent View'!C22 -> 5000 | D14: 5000 | E14: =C14-D14 -> 0 | F14: ='Agent View'!D22 -> 290.155 | G14: =B14-D14-F14 -> 4704.845 | H14: ='Agent View'!F22 -> 2352.4225 | I14: =G14-H14 -> 2352.4225
A16: SCENARIO COMPARISON — company net per deal (monthly), by commission split
A17: Split LOW | B17: 0.5 | D17: Split HIGH | E17: 0.6
A18: Tier | B18: True gross profit/mo | C18: Co. net A) 50/50 | D18: Co. net B) 60 site/50 ent | E18: Co. net C) 50 site/60 ent
A19: Site Starter | B19: =G6 -> 1498.445 | C19: =G6-G6*$B$17 -> 749.2225 | D19: =G6-G6*$E$17 -> 599.378 | E19: =G6-G6*$B$17 -> 749.2225
A20: Site Growth | B20: =G7 -> 1786.845 | C20: =G7-G7*$B$17 -> 893.4225 | D20: =G7-G7*$E$17 -> 714.738 | E20: =G7-G7*$B$17 -> 893.4225
A21: Site Pro | B21: =G8 -> 3378.845 | C21: =G8-G8*$B$17 -> 1689.4225 | D21: =G8-G8*$E$17 -> 1351.538 | E21: =G8-G8*$B$17 -> 1689.4225
A22: Ent Starter | B22: =G12 -> 2641.145 | C22: =G12-G12*$B$17 -> 1320.5725 | D22: =G12-G12*$B$17 -> 1320.5725 | E22: =G12-G12*$E$17 -> 1056.458
A23: Ent Growth | B23: =G13 -> 3874.445 | C23: =G13-G13*$B$17 -> 1937.2225 | D23: =G13-G13*$B$17 -> 1937.2225 | E23: =G13-G13*$E$17 -> 1549.778
A24: Ent Pro | B24: =G14 -> 4704.845 | C24: =G14-G14*$B$17 -> 2352.4225 | D24: =G14-G14*$B$17 -> 2352.4225 | E24: =G14-G14*$E$17 -> 1881.938
